csv_to_json/__init__.py
csv_to_json/csv_to_json.py
csv_to_json/hello_world.py
CSV_to_JSON_Python-901.dist-info/LICENSE.txt
CSV_to_JSON_Python-901.dist-info/METADATA
CSV_to_JSON_Python-901.dist-info/WHEEL
CSV_to_JSON_Python-901.dist-info/top_level.txt
CSV_to_JSON_Python-901.dist-info/RECORD
